{
  "id": "4207911",
  "name": "cheney-project",
  "font_family": "iconfont",
  "css_prefix_text": "icon-",
  "description": "",
  "glyphs": [
    {
      "icon_id": "15838525",
      "name": "search",
      "font_class": "search",
      "unicode": "e67d",
      "unicode_decimal": 59005
    },
    {
      "icon_id": "15838566",
      "name": "arrow-right-bold",
      "font_class": "arrow-right-bold",
      "unicode": "e687",
      "unicode_decimal": 59015
    },
    {
      "icon_id": "15838584",
      "name": "arrow-right-filling",
      "font_class": "arrow-right-filling",
      "unicode": "e688",
      "unicode_decimal": 59016
    }
  ]
}
